aws_lambda_utils/__init__.py
aws_lambda_utils/events/__init__.py
aws_lambda_utils/events/api_gateway/__init__.py
aws_lambda_utils/events/api_gateway/http_proxy/__init__.py
aws_lambda_utils/events/api_gateway/http_proxy/v2/__init__.py
aws_lambda_utils/events/api_gateway/http_proxy/v2/request.py
aws_lambda_utils/events/api_gateway/http_proxy/v2/response.py
aws_lambda_utils/events/api_gateway/request.py
aws_lambda_utils/events/api_gateway/response.py
aws_lambda_utils/events/common.py
aws_lambda_utils/events/s3.py
aws_lambda_utils/events/ses.py
aws_lambda_utils/events/sns.py
aws_lambda_utils/events/sqs.py
aws_lambda_utils/interfaces/__init__.py
aws_lambda_utils/interfaces/icontext.py
aws_lambda_utils/interfaces/ihandler.py
aws_lambda_utils/sns/__init__.py
aws_lambda_utils/sns/isns.py
aws_lambda_utils/sns/sns.py
aws_lambda_utils/sns/type_defs.py
aws_lambda_utils_python-2.0.3.dist-info/WHEEL
aws_lambda_utils_python-2.0.3.dist-info/METADATA
aws_lambda_utils_python-2.0.3.dist-info/RECORD
