Metadata-Version: 2.1
Name: aws-lambda-utils-python
Version: 2.0.3
Summary: 
Author: nichmorgan-loft
Author-email: nich.morgan@loft.com.br
Requires-Python: >=3.9,<4.0
Classifier: Programming Language :: Python :: 3
Classifier: Programming Language :: Python :: 3.10
Classifier: Programming Language :: Python :: 3.9
Requires-Dist: boto3 (>=1.20.7,<2.0.0)
Requires-Dist: boto3-stubs[essential,sns] (>=1.20.8,<2.0.0)
Requires-Dist: pydantic (>=1.8.2,<2.0.0)
